[
  {
    "id": 1752076613635,
    "userId": 1752036507942,
    "products": [
      {
        "id": 2,
        "title": "Eyeshadow Palette",
        "price": 19.99,
        "description": "The Eyeshadow Palette with Mirror offers a versatile range of eyeshadow shades for creating stunning eye looks. With a built-in mirror, it's convenient for on-the-go makeup application.",
        "stock": 34
      },
      {
        "id": 3,
        "title": "Powder Canister",
        "price": 14.99,
        "description": "The Powder Canister is a finely milled setting powder designed to set makeup and control shine. With a lightweight and translucent formula, it provides a smooth and matte finish.",
        "stock": 89
      }
    ],
    "likedCount": 2
  },
  {
    "id": 1752076814387,
    "userId": 1751988274296,
    "products": [
      {
        "id": 3,
        "title": "Powder Canister",
        "price": 14.99,
        "description": "The Powder Canister is a finely milled setting powder designed to set makeup and control shine. With a lightweight and translucent formula, it provides a smooth and matte finish.",
        "stock": 89
      },
      {
        "id": 5,
        "title": "Red Nail Polish",
        "price": 8.99,
        "description": "The Red Nail Polish offers a rich and glossy red hue for vibrant and polished nails. With a quick-drying formula, it provides a salon-quality finish at home.",
        "stock": 79
      },
      {
        "id": 8,
        "title": "Dior J'adore",
        "price": 89.99,
        "description": "J'adore by Dior is a luxurious and floral fragrance, known for its blend of ylang-ylang, rose, and jasmine. It embodies femininity and sophistication.",
        "stock": 98
      }
    ],
    "likedCount": 3
  },
  {
    "id": 1752644693382,
    "userId": 1752439634615,
    "products": [],
    "likedCount": 0
  }
]